{
  "version": "1.0.0",
  "restore": {
    "projectUniqueName": "E:\\Programming\\Projects\\PlayCatCore\\HW-Web-Template\\Headworks.BackendLayout\\content\\src\\__Project__.Common\\__Project__.Common.csproj",
    "projectName": "__Project__.Common",
    "projectPath": "E:\\Programming\\Projects\\PlayCatCore\\HW-Web-Template\\Headworks.BackendLayout\\content\\src\\__Project__.Common\\__Project__.Common.csproj",
    "outputPath": "E:\\Programming\\Projects\\PlayCatCore\\HW-Web-Template\\Headworks.BackendLayout\\content\\src\\__Project__.Common\\obj\\",
    "projectStyle": "PackageReference",
    "fallbackFolders": [
      "C:\\Program Files\\dotnet\\sdk\\NuGetFallbackFolder"
    ],
    "originalTargetFrameworks": [
      "netstandard2.0"
    ],
    "frameworks": {
      "netstandard2.0": {
        "projectReferences": {}
      }
    },
    "warningProperties": {
      "warnAsError": [
        "NU1605"
      ]
    }
  },
  "frameworks": {
    "netstandard2.0": {
      "dependencies": {
        "Microsoft.Extensions.Logging": {
          "target": "Package",
          "version": "[2.1.1, )"
        },
        "NETStandard.Library": {
          "suppressParent": "All",
          "target": "Package",
          "version": "[2.0.3, )",
          "autoReferenced": true
        },
        "System.ComponentModel.Annotations": {
          "target": "Package",
          "version": "[4.5.0, )"
        }
      },
      "imports": [
        "net461"
      ],
      "assetTargetFallback": true,
      "warn": true
    }
  }
}